Workbook

Sheet 📋 Cover
B2: SHEPHERD CONNECT
B3: Annual Operating Cost Planner — 2,000 Users
B4: RCCG City of David · Safe. Known. Celebrated.
B5: ⚠️ Yellow cells are editable inputs — change them to fit your actual usage
B9: 📌 HOW TO USE THIS FILE
B10: 1. Go to the ⚙️ Assumptions sheet | C10: Change yellow cells to match your church size & usage
B11: 2. Go to 💰 Cost Summary | C11: See the full annual & monthly cost breakdown
B12: 3. Go to 📅 Monthly Schedule | C12: See pay-as-you-go buffer month-by-month
B13: 4. Go to 📲 Termii Calculator | C13: Understand SMS / Email / WhatsApp costs in detail
B15: 📌 INCLUDED SERVICES
B16: Replit Core (hosting + DB + storage) | C16: Platform for running the live app
B17: Termii SMS | C17: OTP, check-in alerts, emergency broadcasts
B18: Termii Email | C18: Notifications, appraisal reports
B19: Termii WhatsApp | C19: Rich-media alerts (requires Business API approval)
B20: Domain name (optional) | C20: Custom domain like shepherdconnect.org.ng
B21: PAYG top-up buffer | C21: Reserve to avoid service disruption mid-month

Sheet ⚙️ Assumptions
B1: ⚙️ ASSUMPTIONS — Edit the yellow cells
B2: CHURCH & USER BASE
B3: Total registered users (all roles) | C3: 2000 | D3: ℹ Parents + teachers + admins + attendants
B4: Active parent accounts (receive notifications) | C4: 800 | D4: ℹ Typically 40–50 % of total users
B5: Average children per family | C5: 2 | D5: ℹ Used to estimate check-in volumes
B6: Sunday services per month | C6: 4 | D6: ℹ Usually 4, some months 5
B7: Attendance rate (% of families per service) | C7: 0.7 | D7: ℹ 70 % = 560 families attend each Sunday
B9: TERMII SMS
B10: Termii SMS rate per message (USD) | C10: 0.04 | D10: ℹ Check Termii dashboard · adjust if you get a volume discount
B11: SMS per check-in event (per child) | C11: 1 | D11: ℹ 1 SMS to parent on check-in
B12: SMS per check-out event (per child) | C12: 1 | D12: ℹ 1 SMS to parent on pick-up
B13: Emergency broadcast SMS per month | C13: 2 | D13: ℹ Avg number of emergency alerts per month
B14: General broadcast SMS per month (to all parents) | C14: 1 | D14: ℹ Admin-to-parent broadcast messages
B15: OTP delegate pickup % (of weekly check-outs) | C15: 0.05 | D15: ℹ 5 % use delegate OTP checkout
B17: TERMII EMAIL
B18: Termii email rate per message (USD) | C18: 0.01 | D18: ℹ Check Termii dashboard
B19: Appraisal (Shepherd Report) emails per child/month | C19: 1 | D19: ℹ Monthly report to parents
B20: General notification emails per parent/month | C20: 2 | D20: ℹ Miscellaneous email alerts
B22: TERMII WHATSAPP
B23: WhatsApp enabled? | C23: NO | D23: ℹ YES or NO — requires approved WhatsApp Business API
B24: Termii WhatsApp rate per message (USD) | C24: 0.07 | D24: ℹ Approx. Meta conversation rate for Nigeria
B25: WhatsApp messages per parent per month | C25: 4 | D25: ℹ Check-in alert + report + 2 broadcasts
B27: PLATFORM (REPLIT)
B28: Replit Core plan — monthly cost (USD) | C28: 18 | D28: ℹ Billed annually = $216/yr · includes DB, storage, 3 deployments
B30: DOMAIN (OPTIONAL)
B31: Custom domain cost per year (USD) | C31: 15 | D31: ℹ e.g. shepherdconnect.org.ng — 0 if using .replit.app
B33: PAY-AS-YOU-GO BUFFER
B34: PAYG monthly buffer (% on top of estimated Termii cost) | C34: 0.2 | D34: ℹ 20 % extra credit to avoid running out mid-month
B35: Buffer pre-load months (upfront credit purchase) | C35: 2 | D35: ℹ Buy 2 months of Termii credit upfront as reserve

Sheet 💰 Cost Summary
B1: 💰 ANNUAL COST SUMMARY — Shepherd Connect (2,000 Users)
B2: Cost Item | C2: Monthly (USD) | D2: Annual (USD) | E2: Notes
B3: 1. PLATFORM — Replit Core
B4: Replit Core (hosting + DB + storage + deployments) | C4: ='⚙️ Assumptions'!C28 | D4: ='⚙️ Assumptions'!C28*12 | E4: billed $216/yr — includes PostgreSQL, object storage, 3 deployments
B5: 2. TERMII — SMS Notifications
B6: SMS — check-in / check-out / OTP / broadcasts | C6: =F6*'⚙️ Assumptions'!C10 | D6: =C6*12 | E6: Volume auto-calculated from Assumptions | F6: =ROUND(('⚙️ Assumptions'!C4*'⚙️ Assumptions'!C7*'⚙️ Assumptions'!C5*'⚙️ Assumptions'!C6*('⚙️ Assumptions'!C11+'⚙️ Assumptions'!C12))+('⚙️ Assumptions'!C4*'⚙️ Assumptions'!C13)+('⚙️ Assumptions'!C4*'⚙️ Assumptions'!C14)+('⚙️ Assumptions'!C4*'⚙️ Assumptions'!C7*'⚙️ Assumptions'!C5*'⚙️ Assumptions'!C6*'⚙️ Assumptions'!C15),0)
B7: ↳ Estimated SMS messages per month | C7: =F6 | D7: =F6*12 | E7: Change attendance rate & family size in Assumptions
B8: 3. TERMII — Email Notifications
B9: Email — Shepherd Reports + general notifications | C9: =F9*'⚙️ Assumptions'!C18 | D9: =C9*12 | F9: =ROUND('⚙️ Assumptions'!C4*'⚙️ Assumptions'!C5*'⚙️ Assumptions'!C19+'⚙️ Assumptions'!C4*'⚙️ Assumptions'!C20,0)
B10: ↳ Estimated emails per month | C10: =F9 | D10: =F9*12
B11: 4. TERMII — WhatsApp (requires Business API approval)
B12: WhatsApp — check-in alerts + reports + broadcasts | C12: =F12*'⚙️ Assumptions'!C24 | D12: =C12*12 | E12: Set WhatsApp enabled? = YES in Assumptions to activate | F12: =IF('⚙️ Assumptions'!C23="YES",ROUND('⚙️ Assumptions'!C4*'⚙️ Assumptions'!C25,0),0)
B13: ↳ Estimated WA messages per month | C13: =F12 | D13: =F12*12
B14: 5. PAY-AS-YOU-GO BUFFER (Reserve Credit)
B15: Termii PAYG buffer (% on top of monthly Termii cost) | C15: =(C6+C9+C12)*'⚙️ Assumptions'!C34 | D15: =(C6+C9+C12)*'⚙️ Assumptions'!C34*12 | E15: Prevents service disruption if usage spikes mid-month
B16: Upfront pre-load (buffer months of Termii credit bought on day 1) | C16: — | D16: =(C6+C9+C12)*(1+'⚙️ Assumptions'!C34)*'⚙️ Assumptions'!C35 | E16: One-time extra credit purchase as safety reserve
B17: 6. OPTIONAL — Custom Domain Name
B18: Custom domain (e.g. shepherdconnect.org.ng) | C18: =ROUND('⚙️ Assumptions'!C31/12,2) | D18: ='⚙️ Assumptions'!C31 | E18: Set to 0 in Assumptions if using free .replit.app domain
B21: 🔷 TOTAL ESTIMATED ANNUAL COST (excl. upfront buffer) | C21: =C4+C6+C9+C12+C15+ROUND('⚙️ Assumptions'!C31/12,2) | D21: =D4+D6+D9+D12+D15+'⚙️ Assumptions'!C31
B22: ⭐ FIRST-YEAR TOTAL (includes upfront pre-load buffer) | C22: — | D22: =D21+D16
B24: 💡 Exchange rate: All costs above are in USD. Convert to NGN at the rate of your choice. At ₦1,600/$1, multiply any USD figure by 1600.

Sheet 📲 Termii Calculator
B1: 📲 TERMII USAGE DETAIL & RATE CARD
B2: Channel | C2: Messages/Month | D2: Rate (USD) | E2: Monthly Cost | F2: Annual Cost
B3: SMS MESSAGES
B4: Check-in SMS (parent alert on child arrival) | C4: =ROUND('⚙️ Assumptions'!C4*'⚙️ Assumptions'!C7*'⚙️ Assumptions'!C5*'⚙️ Assumptions'!C6*'⚙️ Assumptions'!C11,0) | D4: ='⚙️ Assumptions'!C10 | E4: =C4*D4 | F4: =E4*12
B5: Check-out SMS (parent alert on pick-up) | C5: =ROUND('⚙️ Assumptions'!C4*'⚙️ Assumptions'!C7*'⚙️ Assumptions'!C5*'⚙️ Assumptions'!C6*'⚙️ Assumptions'!C12,0) | D5: ='⚙️ Assumptions'!C10 | E5: =C5*D5 | F5: =E5*12
B6: Emergency broadcast (to all parents) | C6: =ROUND('⚙️ Assumptions'!C4*'⚙️ Assumptions'!C13,0) | D6: ='⚙️ Assumptions'!C10 | E6: =C6*D6 | F6: =E6*12
B7: Admin broadcast (to all parents) | C7: =ROUND('⚙️ Assumptions'!C4*'⚙️ Assumptions'!C14,0) | D7: ='⚙️ Assumptions'!C10 | E7: =C7*D7 | F7: =E7*12
B8: OTP delegate checkout SMS | C8: =ROUND('⚙️ Assumptions'!C4*'⚙️ Assumptions'!C7*'⚙️ Assumptions'!C5*'⚙️ Assumptions'!C6*'⚙️ Assumptions'!C15,0) | D8: ='⚙️ Assumptions'!C10 | E8: =C8*D8 | F8: =E8*12
B9: SMS Sub-total | C9: =SUM(C4:C8) | D9: — | E9: =SUM(E4:E8) | F9: =E9*12
B11: EMAIL NOTIFICATIONS
B12: Shepherd Report (appraisal) emails to parents | C12: =ROUND('⚙️ Assumptions'!C4*'⚙️ Assumptions'!C5*'⚙️ Assumptions'!C19,0) | D12: ='⚙️ Assumptions'!C18 | E12: =C12*D12 | F12: =E12*12
B13: General notification emails | C13: =ROUND('⚙️ Assumptions'!C4*'⚙️ Assumptions'!C20,0) | D13: ='⚙️ Assumptions'!C18 | E13: =C13*D13 | F13: =E13*12
B14: Email Sub-total | C14: =SUM(C12:C13) | D14: — | E14: =SUM(E12:E13) | F14: =E14*12
B16: WHATSAPP (set 'WhatsApp enabled? = YES' in Assumptions to activate)
B17: WhatsApp messages (check-in, reports, broadcasts) | C17: =IF('⚙️ Assumptions'!C23="YES",ROUND('⚙️ Assumptions'!C4*'⚙️ Assumptions'!C25,0),0) | D17: ='⚙️ Assumptions'!C24 | E17: =C17*D17 | F17: =E17*12
B18: WhatsApp Sub-total | C18: =C17 | D18: — | E18: =E17 | F18: =E18*12
B20: 🔷 TERMII TOTAL | C20: — | D20: — | E20: =E9+E14+E18 | F20: =F9+F14+F18
B22: 📌 Termii PAYG plans: purchase credit in bundles — $10, $25, $50, $100, $200. Unused credit rolls over. Rates above are Termii's standard rates; request a volume discount if monthly SMS > 5,000.
B23: 📌 WhatsApp requires Meta-approved WhatsApp Business API. Termii acts as BSP (Business Solution Provider). Apply at api.termii.com. Not available on a trial Termii account.

Sheet 📅 Monthly Schedule
B1: 📅 MONTHLY CASH FLOW SCHEDULE — 12 Months
B2: Month | C2: Replit | D2: SMS Cost | E2: Email Cost | F2: WA Cost | G2: PAYG Buffer | H2: Month Total | I2: Cumulative
B3: January | C3: ='💰 Cost Summary'!C4 | D3: ='💰 Cost Summary'!C6 | E3: ='💰 Cost Summary'!C9 | F3: ='💰 Cost Summary'!C12 | G3: ='💰 Cost Summary'!C15 | H3: =SUM(C3:G3) | I3: =H3
B4: February | C4: ='💰 Cost Summary'!C4 | D4: ='💰 Cost Summary'!C6 | E4: ='💰 Cost Summary'!C9 | F4: ='💰 Cost Summary'!C12 | G4: ='💰 Cost Summary'!C15 | H4: =SUM(C4:G4) | I4: =I3+H4
B5: March | C5: ='💰 Cost Summary'!C4 | D5: ='💰 Cost Summary'!C6 | E5: ='💰 Cost Summary'!C9 | F5: ='💰 Cost Summary'!C12 | G5: ='💰 Cost Summary'!C15 | H5: =SUM(C5:G5) | I5: =I4+H5
B6: April | C6: ='💰 Cost Summary'!C4 | D6: ='💰 Cost Summary'!C6 | E6: ='💰 Cost Summary'!C9 | F6: ='💰 Cost Summary'!C12 | G6: ='💰 Cost Summary'!C15 | H6: =SUM(C6:G6) | I6: =I5+H6
B7: May | C7: ='💰 Cost Summary'!C4 | D7: ='💰 Cost Summary'!C6 | E7: ='💰 Cost Summary'!C9 | F7: ='💰 Cost Summary'!C12 | G7: ='💰 Cost Summary'!C15 | H7: =SUM(C7:G7) | I7: =I6+H7
B8: June | C8: ='💰 Cost Summary'!C4 | D8: ='💰 Cost Summary'!C6 | E8: ='💰 Cost Summary'!C9 | F8: ='💰 Cost Summary'!C12 | G8: ='💰 Cost Summary'!C15 | H8: =SUM(C8:G8) | I8: =I7+H8
B9: July | C9: ='💰 Cost Summary'!C4 | D9: ='💰 Cost Summary'!C6 | E9: ='💰 Cost Summary'!C9 | F9: ='💰 Cost Summary'!C12 | G9: ='💰 Cost Summary'!C15 | H9: =SUM(C9:G9) | I9: =I8+H9
B10: August | C10: ='💰 Cost Summary'!C4 | D10: ='💰 Cost Summary'!C6 | E10: ='💰 Cost Summary'!C9 | F10: ='💰 Cost Summary'!C12 | G10: ='💰 Cost Summary'!C15 | H10: =SUM(C10:G10) | I10: =I9+H10
B11: September | C11: ='💰 Cost Summary'!C4 | D11: ='💰 Cost Summary'!C6 | E11: ='💰 Cost Summary'!C9 | F11: ='💰 Cost Summary'!C12 | G11: ='💰 Cost Summary'!C15 | H11: =SUM(C11:G11) | I11: =I10+H11
B12: October | C12: ='💰 Cost Summary'!C4 | D12: ='💰 Cost Summary'!C6 | E12: ='💰 Cost Summary'!C9 | F12: ='💰 Cost Summary'!C12 | G12: ='💰 Cost Summary'!C15 | H12: =SUM(C12:G12) | I12: =I11+H12
B13: November | C13: ='💰 Cost Summary'!C4 | D13: ='💰 Cost Summary'!C6 | E13: ='💰 Cost Summary'!C9 | F13: ='💰 Cost Summary'!C12 | G13: ='💰 Cost Summary'!C15 | H13: =SUM(C13:G13) | I13: =I12+H13
B14: December | C14: ='💰 Cost Summary'!C4 | D14: ='💰 Cost Summary'!C6 | E14: ='💰 Cost Summary'!C9 | F14: ='💰 Cost Summary'!C12 | G14: ='💰 Cost Summary'!C15 | H14: =SUM(C14:G14) | I14: =I13+H14
B15: ANNUAL TOTAL | C15: =SUM(C3:C14) | D15: =SUM(D3:D14) | E15: =SUM(E3:E14) | F15: =SUM(F3:F14) | G15: =SUM(G3:G14) | H15: =SUM(H3:H14)
B17: ⭐ First-year cost also includes one-time upfront Termii pre-load buffer (see '💰 Cost Summary' sheet · '⭐ FIRST-YEAR TOTAL' row).
B18: 💡 PAYG top-up tip: When your Termii balance drops below the monthly buffer amount, top up immediately. Set a Termii low-balance alert in the dashboard to get notified before you run out. Recommended minimum top-up: $50 at a time.

Sheet 🇳🇬 NGN Conversion
B1: 🇳🇬 NGN COST CONVERSION
B3: USD to NGN exchange rate (editable) | C3: 1620
B5: Item | C5: USD | D5: NGN (estimated)
B6: Replit (annual) | C6: ='💰 Cost Summary'!D4 | D6: =C6*C3
B7: Termii SMS (annual) | C7: ='💰 Cost Summary'!D6 | D7: =C7*C3
B8: Termii Email (annual) | C8: ='💰 Cost Summary'!D9 | D8: =C8*C3
B9: Termii WhatsApp (annual) | C9: ='💰 Cost Summary'!D12 | D9: =C9*C3
B10: PAYG Buffer (annual) | C10: ='💰 Cost Summary'!D15 | D10: =C10*C3
B11: Custom Domain (annual) | C11: ='⚙️ Assumptions'!C31 | D11: =C11*C3
B12: ANNUAL TOTAL | C12: =SUM(C6:C11) | D12: =C12*C3
B14: 📌 NGN/USD rate fluctuates daily. Update cell C3 to the current CBN rate before budgeting. Check at cbn.gov.ng or Google.
