Workbook

Sheet 📋 Cover
B2: SHEPHERD CONNECT
B3: Annual Operating Cost Planner — 2,000 Users
B4: RCCG City of David · Safe. Known. Celebrated.
B5: ⚠️ Yellow cells are editable inputs — change them to fit your actual usage
B9: 📌 HOW TO USE THIS FILE
B10: 1. Go to the ⚙️ Assumptions sheet | C10: Change yellow cells to match your church size & usage
B11: 2. Go to 💰 Cost Summary | C11: See the full annual & monthly cost breakdown
B12: 3. Go to 📅 Monthly Schedule | C12: See pay-as-you-go buffer month-by-month
B13: 4. Go to 📲 Termii Calculator | C13: Understand SMS / Email / WhatsApp costs in detail
B15: 📌 INCLUDED SERVICES
B16: Replit Core (hosting + DB + storage) | C16: Platform for running the live app
B17: Termii SMS | C17: OTP, check-in alerts, emergency broadcasts
B18: Termii Email | C18: Notifications, appraisal reports
B19: Termii WhatsApp | C19: Rich-media alerts (requires Business API approval)
B20: Domain name (optional) | C20: Custom domain like shepherdconnect.org.ng
B21: PAYG top-up buffer | C21: Reserve to avoid service disruption mid-month

Sheet ⚙️ Assumptions
B1: ⚙️ ASSUMPTIONS — Edit the yellow cells
B2: CHURCH & USER BASE
B3: Total registered users (all roles) | C3: 800 | D3: ℹ Parents + teachers + admins + attendants
B4: Active parent accounts (receive notifications) | C4: 400 | D4: ℹ Typically 40–50 % of total users
B5: Average children per family | C5: 2 | D5: ℹ Used to estimate check-in volumes
B6: Sunday services per month | C6: 4 | D6: ℹ Usually 4, some months 5
B7: Attendance rate (% of families per service) | C7: 0.7 | D7: ℹ 70 % = 560 families attend each Sunday
B9: TERMII SMS
B10: Termii SMS rate per message (USD) | C10: 0.025 | D10: ℹ Check Termii dashboard · adjust if you get a volume discount
B11: SMS per check-in event (per child) | C11: 1 | D11: ℹ 1 SMS to parent on check-in
B12: SMS per check-out event (per child) | C12: 1 | D12: ℹ 1 SMS to parent on pick-up
B13: Emergency broadcast SMS per month | C13: 2 | D13: ℹ Avg number of emergency alerts per month
B14: General broadcast SMS per month (to all parents) | C14: 1 | D14: ℹ Admin-to-parent broadcast messages
B15: OTP delegate pickup % (of weekly check-outs) | C15: 0.05 | D15: ℹ 5 % use delegate OTP checkout
B17: TERMII EMAIL
B18: Termii email rate per message (USD) | C18: 0.0009 | D18: ℹ Check Termii dashboard
B19: Appraisal (Shepherd Report) emails per child/month | C19: 1 | D19: ℹ Monthly report to parents
B20: General notification emails per parent/month | C20: 2 | D20: ℹ Miscellaneous email alerts
B22: TERMII WHATSAPP
B23: WhatsApp enabled? | C23: NO | D23: ℹ YES or NO — requires approved WhatsApp Business API
B24: Termii WhatsApp rate per message (USD) | C24: 0.0036 | D24: ℹ Approx. Meta conversation rate for Nigeria
B25: WhatsApp messages per parent per month | C25: 4 | D25: ℹ Check-in alert + report + 2 broadcasts
B27: PLATFORM (REPLIT)
B28: Replit Core plan — monthly cost (USD) | C28: 18 | D28: ℹ Billed annually = $216/yr · includes DB, storage, 3 deployments
B30: DOMAIN (OPTIONAL)
B31: Custom domain cost per year (USD) | C31: 15 | D31: ℹ e.g. shepherdconnect.org.ng — 0 if using .replit.app
B33: PAY-AS-YOU-GO BUFFER
B34: PAYG monthly buffer (% on top of estimated Termii cost) | C34: 0.2 | D34: ℹ 20 % extra credit to avoid running out mid-month
B35: Buffer pre-load months (upfront credit purchase) | C35: 2 | D35: ℹ Buy 2 months of Termii credit upfront as reserve

Sheet 💰 Cost Summary
B1: 💰 ANNUAL COST SUMMARY — Shepherd Connect (2,000 Users)
B2: Cost Item | C2: Monthly (USD) | D2: Annual (USD) | E2: Notes
B3: 1. PLATFORM — Replit Core
B4: Replit Core (hosting + DB + storage + deployments) | C4: ='⚙️ Assumptions'!C28 -> 18 | D4: ='⚙️ Assumptions'!C28*12 -> 216 | E4: billed $216/yr — includes PostgreSQL, object storage, 3 deployments
B5: 2. TERMII — SMS Notifications
B6: SMS — check-in / check-out / OTP / broadcasts | C6: =F6*'⚙️ Assumptions'!C10 -> 144.8 | D6: =C6*12 -> 1737.6 | E6: Volume auto-calculated from Assumptions | F6: =ROUND(('⚙️ Assumptions'!C4*'⚙️ Assumptions'!C7*'⚙️ Assumptions'!C5*'⚙️ Assumptions'!C6*('⚙️ Assumptions'!C11+'⚙️ Assumptions'!C12))+('⚙️ Assumptions'!C4*'⚙️ Assumptions'!C13)+('⚙️ Assumptions'!C4*'⚙️ Assumptions'!C14)+('⚙️ Assumptions'!C4*'⚙️ Assumptions'!C7*'⚙️ Assumptions'!C5*'⚙️ Assumptions'!C6*'⚙️ Assumptions'!C15),0) -> 5792
B7: ↳ Estimated SMS messages per month | C7: =F6 -> 5792 | D7: =F6*12 -> 69504 | E7: Change attendance rate & family size in Assumptions
B8: 3. TERMII — Email Notifications
B9: Email — Shepherd Reports + general notifications | C9: =F9*'⚙️ Assumptions'!C18 -> 1.44 | D9: =C9*12 -> 17.28 | F9: =ROUND('⚙️ Assumptions'!C4*'⚙️ Assumptions'!C5*'⚙️ Assumptions'!C19+'⚙️ Assumptions'!C4*'⚙️ Assumptions'!C20,0) -> 1600
B10: ↳ Estimated emails per month | C10: =F9 -> 1600 | D10: =F9*12 -> 19200
B11: 4. TERMII — WhatsApp (requires Business API approval)
B12: WhatsApp — check-in alerts + reports + broadcasts | C12: =F12*'⚙️ Assumptions'!C24 -> 0 | D12: =C12*12 -> 0 | E12: Set WhatsApp enabled? = YES in Assumptions to activate | F12: =IF('⚙️ Assumptions'!C23="YES",ROUND('⚙️ Assumptions'!C4*'⚙️ Assumptions'!C25,0),0) -> 0
B13: ↳ Estimated WA messages per month | C13: =F12 -> 0 | D13: =F12*12 -> 0
B14: 5. PAY-AS-YOU-GO BUFFER (Reserve Credit)
B15: Termii PAYG buffer (% on top of monthly Termii cost) | C15: =(C6+C9+C12)*'⚙️ Assumptions'!C34 -> 29.248 | D15: =(C6+C9+C12)*'⚙️ Assumptions'!C34*12 -> 350.976 | E15: Prevents service disruption if usage spikes mid-month
B16: Upfront pre-load (buffer months of Termii credit bought on day 1) | C16: — | D16: =(C6+C9+C12)*(1+'⚙️ Assumptions'!C34)*'⚙️ Assumptions'!C35 -> 350.976 | E16: One-time extra credit purchase as safety reserve
B17: 6. OPTIONAL — Custom Domain Name
B18: Custom domain (e.g. shepherdconnect.org.ng) | C18: =ROUND('⚙️ Assumptions'!C31/12,2) -> 1.25 | D18: ='⚙️ Assumptions'!C31 -> 15 | E18: Set to 0 in Assumptions if using free .replit.app domain
B21: 🔷 TOTAL ESTIMATED ANNUAL COST (excl. upfront buffer) | C21: =C4+C6+C9+C12+C15+ROUND('⚙️ Assumptions'!C31/12,2) -> 194.738 | D21: =D4+D6+D9+D12+D15+'⚙️ Assumptions'!C31 -> 2336.856
B22: ⭐ FIRST-YEAR TOTAL (includes upfront pre-load buffer) | C22: — | D22: =D21+D16 -> 2687.832
B24: 💡 Exchange rate: All costs above are in USD. Convert to NGN at the rate of your choice. At ₦1,600/$1, multiply any USD figure by 1600.

Sheet 📲 Termii Calculator
B1: 📲 TERMII USAGE DETAIL & RATE CARD
B2: Channel | C2: Messages/Month | D2: Rate (USD) | E2: Monthly Cost | F2: Annual Cost
B3: SMS MESSAGES
B4: Check-in SMS (parent alert on child arrival) | C4: =ROUND('⚙️ Assumptions'!C4*'⚙️ Assumptions'!C7*'⚙️ Assumptions'!C5*'⚙️ Assumptions'!C6*'⚙️ Assumptions'!C11,0) -> 2240 | D4: ='⚙️ Assumptions'!C10 -> 0.025 | E4: =C4*D4 -> 56 | F4: =E4*12 -> 672
B5: Check-out SMS (parent alert on pick-up) | C5: =ROUND('⚙️ Assumptions'!C4*'⚙️ Assumptions'!C7*'⚙️ Assumptions'!C5*'⚙️ Assumptions'!C6*'⚙️ Assumptions'!C12,0) -> 2240 | D5: ='⚙️ Assumptions'!C10 -> 0.025 | E5: =C5*D5 -> 56 | F5: =E5*12 -> 672
B6: Emergency broadcast (to all parents) | C6: =ROUND('⚙️ Assumptions'!C4*'⚙️ Assumptions'!C13,0) -> 800 | D6: ='⚙️ Assumptions'!C10 -> 0.025 | E6: =C6*D6 -> 20 | F6: =E6*12 -> 240
B7: Admin broadcast (to all parents) | C7: =ROUND('⚙️ Assumptions'!C4*'⚙️ Assumptions'!C14,0) -> 400 | D7: ='⚙️ Assumptions'!C10 -> 0.025 | E7: =C7*D7 -> 10 | F7: =E7*12 -> 120
B8: OTP delegate checkout SMS | C8: =ROUND('⚙️ Assumptions'!C4*'⚙️ Assumptions'!C7*'⚙️ Assumptions'!C5*'⚙️ Assumptions'!C6*'⚙️ Assumptions'!C15,0) -> 112 | D8: ='⚙️ Assumptions'!C10 -> 0.025 | E8: =C8*D8 -> 2.8 | F8: =E8*12 -> 33.6
B9: SMS Sub-total | C9: =SUM(C4:C8) -> 5792 | D9: — | E9: =SUM(E4:E8) -> 144.8 | F9: =E9*12 -> 1737.6
B11: EMAIL NOTIFICATIONS
B12: Shepherd Report (appraisal) emails to parents | C12: =ROUND('⚙️ Assumptions'!C4*'⚙️ Assumptions'!C5*'⚙️ Assumptions'!C19,0) -> 800 | D12: ='⚙️ Assumptions'!C18 -> 0.0009 | E12: =C12*D12 -> 0.72 | F12: =E12*12 -> 8.64
B13: General notification emails | C13: =ROUND('⚙️ Assumptions'!C4*'⚙️ Assumptions'!C20,0) -> 800 | D13: ='⚙️ Assumptions'!C18 -> 0.0009 | E13: =C13*D13 -> 0.72 | F13: =E13*12 -> 8.64
B14: Email Sub-total | C14: =SUM(C12:C13) -> 1600 | D14: — | E14: =SUM(E12:E13) -> 1.44 | F14: =E14*12 -> 17.28
B16: WHATSAPP (set 'WhatsApp enabled? = YES' in Assumptions to activate)
B17: WhatsApp messages (check-in, reports, broadcasts) | C17: =IF('⚙️ Assumptions'!C23="YES",ROUND('⚙️ Assumptions'!C4*'⚙️ Assumptions'!C25,0),0) -> 0 | D17: ='⚙️ Assumptions'!C24 -> 0.0036 | E17: =C17*D17 -> 0 | F17: =E17*12 -> 0
B18: WhatsApp Sub-total | C18: =C17 -> 0 | D18: — | E18: =E17 -> 0 | F18: =E18*12 -> 0
B20: 🔷 TERMII TOTAL | C20: — | D20: — | E20: =E9+E14+E18 -> 146.24 | F20: =F9+F14+F18 -> 1754.88
B22: 📌 Termii PAYG plans: purchase credit in bundles — $10, $25, $50, $100, $200. Unused credit rolls over. Rates above are Termii's standard rates; request a volume discount if monthly SMS > 5,000.
B23: 📌 WhatsApp requires Meta-approved WhatsApp Business API. Termii acts as BSP (Business Solution Provider). Apply at api.termii.com. Not available on a trial Termii account.

Sheet 📅 Monthly Schedule
B1: 📅 MONTHLY CASH FLOW SCHEDULE — 12 Months
B2: Month | C2: Replit | D2: SMS Cost | E2: Email Cost | F2: WA Cost | G2: PAYG Buffer | H2: Month Total | I2: Cumulative
B3: January | C3: ='💰 Cost Summary'!C4 -> 18 | D3: ='💰 Cost Summary'!C6 -> 144.8 | E3: ='💰 Cost Summary'!C9 -> 1.44 | F3: ='💰 Cost Summary'!C12 -> 0 | G3: ='💰 Cost Summary'!C15 -> 29.248 | H3: =SUM(C3:G3) -> 193.488 | I3: =H3 -> 193.488
B4: February | C4: ='💰 Cost Summary'!C4 -> 18 | D4: ='💰 Cost Summary'!C6 -> 144.8 | E4: ='💰 Cost Summary'!C9 -> 1.44 | F4: ='💰 Cost Summary'!C12 -> 0 | G4: ='💰 Cost Summary'!C15 -> 29.248 | H4: =SUM(C4:G4) -> 193.488 | I4: =I3+H4 -> 386.976
B5: March | C5: ='💰 Cost Summary'!C4 -> 18 | D5: ='💰 Cost Summary'!C6 -> 144.8 | E5: ='💰 Cost Summary'!C9 -> 1.44 | F5: ='💰 Cost Summary'!C12 -> 0 | G5: ='💰 Cost Summary'!C15 -> 29.248 | H5: =SUM(C5:G5) -> 193.488 | I5: =I4+H5 -> 580.464
B6: April | C6: ='💰 Cost Summary'!C4 -> 18 | D6: ='💰 Cost Summary'!C6 -> 144.8 | E6: ='💰 Cost Summary'!C9 -> 1.44 | F6: ='💰 Cost Summary'!C12 -> 0 | G6: ='💰 Cost Summary'!C15 -> 29.248 | H6: =SUM(C6:G6) -> 193.488 | I6: =I5+H6 -> 773.952
B7: May | C7: ='💰 Cost Summary'!C4 -> 18 | D7: ='💰 Cost Summary'!C6 -> 144.8 | E7: ='💰 Cost Summary'!C9 -> 1.44 | F7: ='💰 Cost Summary'!C12 -> 0 | G7: ='💰 Cost Summary'!C15 -> 29.248 | H7: =SUM(C7:G7) -> 193.488 | I7: =I6+H7 -> 967.44
B8: June | C8: ='💰 Cost Summary'!C4 -> 18 | D8: ='💰 Cost Summary'!C6 -> 144.8 | E8: ='💰 Cost Summary'!C9 -> 1.44 | F8: ='💰 Cost Summary'!C12 -> 0 | G8: ='💰 Cost Summary'!C15 -> 29.248 | H8: =SUM(C8:G8) -> 193.488 | I8: =I7+H8 -> 1160.928
B9: July | C9: ='💰 Cost Summary'!C4 -> 18 | D9: ='💰 Cost Summary'!C6 -> 144.8 | E9: ='💰 Cost Summary'!C9 -> 1.44 | F9: ='💰 Cost Summary'!C12 -> 0 | G9: ='💰 Cost Summary'!C15 -> 29.248 | H9: =SUM(C9:G9) -> 193.488 | I9: =I8+H9 -> 1354.416
B10: August | C10: ='💰 Cost Summary'!C4 -> 18 | D10: ='💰 Cost Summary'!C6 -> 144.8 | E10: ='💰 Cost Summary'!C9 -> 1.44 | F10: ='💰 Cost Summary'!C12 -> 0 | G10: ='💰 Cost Summary'!C15 -> 29.248 | H10: =SUM(C10:G10) -> 193.488 | I10: =I9+H10 -> 1547.904
B11: September | C11: ='💰 Cost Summary'!C4 -> 18 | D11: ='💰 Cost Summary'!C6 -> 144.8 | E11: ='💰 Cost Summary'!C9 -> 1.44 | F11: ='💰 Cost Summary'!C12 -> 0 | G11: ='💰 Cost Summary'!C15 -> 29.248 | H11: =SUM(C11:G11) -> 193.488 | I11: =I10+H11 -> 1741.392
B12: October | C12: ='💰 Cost Summary'!C4 -> 18 | D12: ='💰 Cost Summary'!C6 -> 144.8 | E12: ='💰 Cost Summary'!C9 -> 1.44 | F12: ='💰 Cost Summary'!C12 -> 0 | G12: ='💰 Cost Summary'!C15 -> 29.248 | H12: =SUM(C12:G12) -> 193.488 | I12: =I11+H12 -> 1934.88
B13: November | C13: ='💰 Cost Summary'!C4 -> 18 | D13: ='💰 Cost Summary'!C6 -> 144.8 | E13: ='💰 Cost Summary'!C9 -> 1.44 | F13: ='💰 Cost Summary'!C12 -> 0 | G13: ='💰 Cost Summary'!C15 -> 29.248 | H13: =SUM(C13:G13) -> 193.488 | I13: =I12+H13 -> 2128.368
B14: December | C14: ='💰 Cost Summary'!C4 -> 18 | D14: ='💰 Cost Summary'!C6 -> 144.8 | E14: ='💰 Cost Summary'!C9 -> 1.44 | F14: ='💰 Cost Summary'!C12 -> 0 | G14: ='💰 Cost Summary'!C15 -> 29.248 | H14: =SUM(C14:G14) -> 193.488 | I14: =I13+H14 -> 2321.856
B15: ANNUAL TOTAL | C15: =SUM(C3:C14) -> 216 | D15: =SUM(D3:D14) -> 1737.6 | E15: =SUM(E3:E14) -> 17.28 | F15: =SUM(F3:F14) -> 0 | G15: =SUM(G3:G14) -> 350.976 | H15: =SUM(H3:H14) -> 2321.856
B17: ⭐ First-year cost also includes one-time upfront Termii pre-load buffer (see '💰 Cost Summary' sheet · '⭐ FIRST-YEAR TOTAL' row).
B18: 💡 PAYG top-up tip: When your Termii balance drops below the monthly buffer amount, top up immediately. Set a Termii low-balance alert in the dashboard to get notified before you run out. Recommended minimum top-up: $50 at a time.

Sheet 🇳🇬 NGN Conversion
B1: 🇳🇬 NGN COST CONVERSION
B3: USD to NGN exchange rate (editable) | C3: 1620
B5: Item | C5: USD | D5: NGN (estimated)
B6: Replit (annual) | C6: ='💰 Cost Summary'!D4 -> 216 | D6: =C6*C3 -> 349920
B7: Termii SMS (annual) | C7: ='💰 Cost Summary'!D6 -> 1737.6 | D7: =C7*C3 -> 2814912
B8: Termii Email (annual) | C8: ='💰 Cost Summary'!D9 -> 17.28 | D8: =C8*C3 -> 27993.6
B9: Termii WhatsApp (annual) | C9: ='💰 Cost Summary'!D12 -> 0 | D9: =C9*C3 -> 0
B10: PAYG Buffer (annual) | C10: ='💰 Cost Summary'!D15 -> 350.976 | D10: =C10*C3 -> 568581.12
B11: Custom Domain (annual) | C11: ='⚙️ Assumptions'!C31 -> 15 | D11: =C11*C3 -> 24300
B12: ANNUAL TOTAL | C12: =SUM(C6:C11) -> 2336.856 | D12: =C12*C3 -> 3785706.7
B14: 📌 NGN/USD rate fluctuates daily. Update cell C3 to the current CBN rate before budgeting. Check at cbn.gov.ng or Google.

Sheet ⚖️ Deployment Comparison
B1: ⚖️ AUTOSCALE (PAYG) vs RESERVED VM — Which is right for you?
B2: Both options require Replit Core ($18/month). Yellow cells are editable estimates.
B4: ⚡ AUTOSCALE (PAYG) | F4: 🖥️ RESERVED VM
B5: Item | C5: Monthly (USD) | D5: Annual (USD) | F5: Item | G5: Monthly (USD) | H5: Annual (USD)
B6: Replit Core subscription | C6: ='💰 Cost Summary'!C4 -> 18 | D6: ='💰 Cost Summary'!D4 -> 216 | F6: Replit Core subscription | G6: ='💰 Cost Summary'!C4 -> 18 | H6: ='💰 Cost Summary'!D4 -> 216
B7: Sunday compute — est. cost per Sunday | C7: 8 | D7: =C7*12 -> 96 | F7: Reserved VM — 1 vCPU / 1 GB ✅ recommended | G7: 10 | H7: =G7*12 -> 120
B8: × avg Sundays per month | C8: 4.3 | D8: =C8*12 -> 51.6 | F8: Reserved VM — 2 vCPU / 2 GB (comfortable headroom) | G8: 20 | H8: =G8*12 -> 240
B9: Sunday compute subtotal | C9: =C7*C8 -> 34.4 | D9: =C7*C8*12 -> 412.8 | F9: → Use ONE of the two tiers above in your budget | G9: — | H9: —
B10: Weekday low-traffic compute (est.) | C10: 2 | D10: =C10*12 -> 24 | F10: Termii (SMS + Email + WA + Buffer) | G10: =('💰 Cost Summary'!C6+'💰 Cost Summary'!C9+'💰 Cost Summary'!C12+'💰 Cost Summary'!C15) -> 175.488 | H10: =('💰 Cost Summary'!D6+'💰 Cost Summary'!D9+'💰 Cost Summary'!D12+'💰 Cost Summary'!D15) -> 2105.856
B11: Termii (SMS + Email + WA + Buffer) | C11: =('💰 Cost Summary'!C6+'💰 Cost Summary'!C9+'💰 Cost Summary'!C12+'💰 Cost Summary'!C15) -> 175.488 | D11: =('💰 Cost Summary'!D6+'💰 Cost Summary'!D9+'💰 Cost Summary'!D12+'💰 Cost Summary'!D15) -> 2105.856 | F11: Custom domain (optional) | G11: =ROUND('⚙️ Assumptions'!C28/12,2) -> 1.5 | H11: ='⚙️ Assumptions'!C28 -> 18
B12: Custom domain (optional) | C12: =ROUND('⚙️ Assumptions'!C28/12,2) -> 1.5 | D12: ='⚙️ Assumptions'!C28 -> 18 | F12: 🖥️ RESERVED VM TOTAL (1 vCPU) | G12: =SUM(G6,G7,G10,G11) -> 204.988 | H12: =SUM(H6,H7,H10,H11) -> 2459.856
B13: ⚡ AUTOSCALE TOTAL | C13: =SUM(C6,C9,C10,C11,C12) -> 231.388 | D13: =SUM(D6,D9,D10,D11,D12) -> 2776.656
B14: 📊 FEATURE & COST COMPARISON
B15: Feature | C15: ⚡ Autoscale | F15: 🖥️ Reserved VM
B16: Billing model | C16: Pay per compute second | F16: Fixed monthly fee
B17: Estimated monthly platform | C17: =C13 -> 231.388 | F17: =G12 -> 204.988
B18: Estimated annual platform | C18: =D13 -> 2776.656 | F18: =H12 -> 2459.856
B19: Possible annual saving | F19: —
B20: Traffic handling | C20: Auto-scales to any demand ✅ | F20: Fixed capacity — sized at setup
B21: Handles Sunday peak? | C21: Yes — scales instantly ✅ | F21: Yes — 1 vCPU handles ~500 concurrent ✅
B22: Idle time billing | C22: Near-zero on quiet weekdays ✅ | F22: Full price 24/7 even when idle
B23: Budget predictability | C23: Varies (~$23–35/mo est.) | F23: 100% fixed — zero surprises ✅
B24: Best for | C24: Low-traffic-except-Sundays pattern ✅ | F24: Church finance team prefers fixed bills ✅
B25: Risk | C25: Surprise bill if unusual event | F25: Over-paying on quiet months
B26: Database included? | C26: Yes (Core plan) ✅ | F26: Yes (Core plan) ✅
B27: Object storage included? | C27: Yes — 50 GB (Core plan) ✅ | F27: Yes — 50 GB (Core plan) ✅
B28: Recommended for 2,000 users? | C28: ✅ Yes | F28: ✅ Yes
B30: ⚠️ Yellow cells are editable. Change Sunday compute cost and VM tier to match your actual Replit bill. Termii figures are pulled live from your Assumptions sheet. Replit publishes current deployment pricing at replit.com/pricing.
